notdiamond_openai/__init__.py
notdiamond_openai/__main__.py
notdiamond_openai/_base_client.py
notdiamond_openai/_client.py
notdiamond_openai/_compat.py
notdiamond_openai/_constants.py
notdiamond_openai/_exceptions.py
notdiamond_openai/_files.py
notdiamond_openai/_legacy_response.py
notdiamond_openai/_models.py
notdiamond_openai/_module_client.py
notdiamond_openai/_qs.py
notdiamond_openai/_resource.py
notdiamond_openai/_response.py
notdiamond_openai/_streaming.py
notdiamond_openai/_types.py
notdiamond_openai/_version.py
notdiamond_openai/pagination.py
notdiamond_openai/py.typed
notdiamond_openai/version.py
notdiamond_openai/_extras/__init__.py
notdiamond_openai/_extras/_common.py
notdiamond_openai/_extras/numpy_proxy.py
notdiamond_openai/_extras/pandas_proxy.py
notdiamond_openai/_utils/__init__.py
notdiamond_openai/_utils/_logs.py
notdiamond_openai/_utils/_proxy.py
notdiamond_openai/_utils/_streams.py
notdiamond_openai/_utils/_sync.py
notdiamond_openai/_utils/_transform.py
notdiamond_openai/_utils/_typing.py
notdiamond_openai/_utils/_utils.py
notdiamond_openai/cli/__init__.py
notdiamond_openai/cli/_cli.py
notdiamond_openai/cli/_errors.py
notdiamond_openai/cli/_models.py
notdiamond_openai/cli/_progress.py
notdiamond_openai/cli/_utils.py
notdiamond_openai/cli/_api/__init__.py
notdiamond_openai/cli/_api/_main.py
notdiamond_openai/cli/_api/audio.py
notdiamond_openai/cli/_api/completions.py
notdiamond_openai/cli/_api/files.py
notdiamond_openai/cli/_api/image.py
notdiamond_openai/cli/_api/models.py
notdiamond_openai/cli/_api/chat/__init__.py
notdiamond_openai/cli/_api/chat/completions.py
notdiamond_openai/cli/_tools/__init__.py
notdiamond_openai/cli/_tools/_main.py
notdiamond_openai/cli/_tools/fine_tunes.py
notdiamond_openai/cli/_tools/migrate.py
notdiamond_openai/lib/.keep
notdiamond_openai/lib/_old_api.py
notdiamond_openai/lib/_validators.py
notdiamond_openai/lib/azure.py
notdiamond_openai/lib/notdiamond/model_select.py
notdiamond_openai/lib/streaming/__init__.py
notdiamond_openai-0.1.4.dist-info/METADATA
notdiamond_openai-0.1.4.dist-info/WHEEL
notdiamond_openai-0.1.4.dist-info/entry_points.txt
notdiamond_openai-0.1.4.dist-info/licenses/LICENSE
notdiamond_openai-0.1.4.dist-info/RECORD
